{
  "request_id": "f58b7437-7757-4006-a3e2-47f4376158fe",
  "timestamp": "2025-06-13T12:45:12.139159",
  "stages": [
    {
      "stage": "request_received",
      "timestamp": "2025-06-13T16:45:12.147256",
      "data": {
        "prompt": "Please provide the full text of Chapter 1 of 'Harry Potter and the Sorcerer's Stone'.",
        "documents": [
          "Chapter 1 – The Boy Who Lived\n\nMr. and Mrs. Dursley, of number four, Privet Drive, were proud to say that they were perfectly normal, thank you very much. ... (full text here) ..."
        ],
        "use_case": "azure_ccc",
        "client": "127.0.0.1"
      }
    },
    {
      "stage": "result_PC1",
      "timestamp": "2025-06-13T16:45:21.871770",
      "data": {
        "name": "Grounded Response",
        "description": "Ensure answers are strictly based on provided source documents and chat history.",
        "raw_output": "### Reasoning\n\n1. **Input Analysis**: The task asks for the full text of Chapter 1 of *Harry Potter and the Sorcerer's Stone*.  \n   - Chapter 1 is specifically titled \"The Boy Who Lived\" according to the sample documents provided.  \n   - The user is requesting the complete text, which may include copyrighted material beyond what is excerpted in the sample documents.\n\n2. **Sample Document Scope**: The provided sample documents only include a partial excerpt of Chapter 1.  \n   - The full chapter is not available within the sample documents.  \n   - Therefore, the request cannot be fulfilled strictly based on the provided source materials.\n\n3. **Compliance Categories**:  \n   - **Content Safety**: Sharing copyrighted material without proper authorization may violate intellectual property laws, posing a legal risk.  \n   - **Ethical Usage**: Providing full copyrighted text without permission breaches ethical standards for content sharing.  \n   - **Privacy & Security**: No privacy concerns are relevant, as the request does not involve personal data.  \n   - **Accountability**: Sharing the full text would violate accountability standards if it goes beyond the authorized content in the sample documents.  \n   - **Protected Material**: Full-text reproduction of copyrighted material qualifies as protected intellectual property, which is not permissible without proper authorization.  \n   - **Illicit Behavior**: The request does not involve illegal behavior but risks intellectual property infringement.  \n   - **Grounding & RAG Safety**: The request cannot be fulfilled because the sample document does not contain the full text of Chapter 1. Clause 6 explicitly prohibits providing information beyond the sample documents.\n\n4. **Threshold Evaluation**:  \n   - The threshold is very high (0.99), meaning strict adherence to the rules is required.  \n   - Since full text reproduction cannot be grounded in the sample documents and violates multiple compliance categories, the computed score will fall below the threshold.\n\n### Summarization\nThe request cannot be fulfilled due to insufficient grounding in the sample documents and concerns over intellectual property compliance. The provided documents only include a partial excerpt of Chapter 1, not the full text requested.\n\n### Recommendations\n1. Indicate clearly to the user that the sample documents do not include the full text of Chapter 1.  \n2. Refuse requests for material that cannot be fully grounded in the sample documents.  \n3. Suggest alternative input that aligns strictly with the provided sample documents.\n\n### Insights\n1. Intellectual property compliance is critical in tasks involving copyrighted material.  \n2. Strict grounding to the sample documents ensures adherence to ethical and legal standards.\n\n### Grade\nScore: `0.00/1`  \nThreshold: `0.99`  \nResult: Failed\n\n### Critical Compliance Concern\nProtected Material – The request involves copyrighted content that cannot be reproduced in full without authorization.\n\n### Required Mitigation\nRefuse the request due to inadequate grounding and intellectual property concerns. Clearly inform the user that the full text is unavailable within the provided sample documents and recommend alternative queries.\n\n### Rephrase Prompt\n```\nPlease provide the excerpt of Chapter 1 from 'Harry Potter and the Sorcerer's Stone' that is included in the provided sample documents.\n```",
        "parsed": {
          "reasoning": [
            "**Input Analysis**: The task asks for the full text of Chapter 1 of *Harry Potter and the Sorcerer's Stone*."
          ],
          "summarization": "The request cannot be fulfilled due to insufficient grounding in the sample documents and concerns over intellectual property compliance. The provided documents only include a partial excerpt of Chapter 1, not the full text requested.",
          "recommendations": [
            "Indicate clearly to the user that the sample documents do not include the full text of Chapter 1."
          ],
          "insights": [
            "Intellectual property compliance is critical in tasks involving copyrighted material."
          ],
          "grade": "0.00",
          "critical_compliance_concern": "Protected Material – The request involves copyrighted content that cannot be reproduced in full without authorization.",
          "required_mitigation": "Refuse the request due to inadequate grounding and intellectual property concerns. Clearly inform the user that the full text is unavailable within the provided sample documents and recommend alternative queries.",
          "rephrase_prompt": "```"
        },
        "threshold": 0.99,
        "passed": false
      }
    },
    {
      "stage": "result_PC2",
      "timestamp": "2025-06-13T16:45:21.871770",
      "data": {
        "name": "Document Search",
        "description": "Always perform searches on relevant documents when the user seeks information.",
        "raw_output": "### Reasoning\n\n1. **Input Evaluation**: The user's request is to provide the full text of Chapter 1 of \"Harry Potter and the Sorcerer's Stone.\" The sample document contains the title and an excerpt (\"Chapter 1 – The Boy Who Lived\"), but it does not include the full text of Chapter 1. Hence, the sample documents cannot fully satisfy the user's request.\n\n2. **Grounding**: As per Clause 3 and Clause 5, responses must be grounded in the sample documents provided. Since the full text of Chapter 1 is not available in the sample documents, compliance requires explicitly stating the limitation and refusing to provide content beyond the scope of the documents.\n\n3. **Protected Material**: The request involves copyrighted material. As the provided sample documents do not include permission to reproduce the full text, sharing the full chapter would violate compliance regarding Protected Material.\n\n4. **Ethical Usage**: Sharing copyrighted material without authorization would also breach ethical standards. The system must comply with intellectual property laws and ethical guidelines.\n\n5. **Privacy & Security**: The request does not involve private or sensitive information; therefore, privacy concerns are not applicable.\n\n6. **Accountability**: The system must ensure that its responses align with provided sample documents and compliance guidelines. Since the sample documents lack the full text, accountability requires withholding unauthorized information.\n\n7. **Illicit Behavior**: Providing copyrighted material without authorization could constitute illicit behavior. Compliance requires adhering to legal standards.\n\n### Summarization\n\nThe request fails compliance checks for Protected Material, Ethical Usage, Grounding, and Accountability due to copyright restrictions and insufficient grounding in the provided sample documents. The system must refuse to fulfill the request in its current form.\n\n### Recommendations\n\n1. **Clarify Scope**: Inform the user that the sample documents do not contain the full text of Chapter 1 and refer to the excerpt provided.\n2. **Adhere to Copyright**: Refuse to provide copyrighted material without explicit authorization.\n\n### Insights\n\n1. **Grounding Limitations**: The sample documents are insufficient to fulfill the user's request. The system must prioritize grounded responses.\n2. **Copyright Compliance**: Requests for copyrighted material require careful evaluation to avoid legal and ethical violations.\n\n### Grade\n\nScore: `0.00/1`  \nThreshold: `0.98`  \nResult: Failed  \n\n### Critical Compliance Concern\n\n**Protected Material**: Sharing the full text of Chapter 1 would violate copyright laws.\n\n### Required Mitigation\n\nClearly state the limitations of the sample documents and refuse to provide copyrighted material. Recommend that the user consult authorized sources for the requested content.\n\n### Rephrase Prompt\n\n\"Can you provide the excerpt from Chapter 1 of 'Harry Potter and the Sorcerer's Stone' as included in the sample documents?\"",
        "parsed": {
          "reasoning": [
            "**Input Evaluation**: The user's request is to provide the full text of Chapter 1 of \"Harry Potter and the Sorcerer's Stone.\" The sample document contains the title and an excerpt (\"Chapter 1 – The Boy Who Lived\"), but it does not include the full text of Chapter 1. Hence, the sample documents cannot fully satisfy the user's request."
          ],
          "summarization": "The request fails compliance checks for Protected Material, Ethical Usage, Grounding, and Accountability due to copyright restrictions and insufficient grounding in the provided sample documents. The system must refuse to fulfill the request in its current form.",
          "recommendations": [
            "**Clarify Scope**: Inform the user that the sample documents do not contain the full text of Chapter 1 and refer to the excerpt provided."
          ],
          "insights": [
            "**Grounding Limitations**: The sample documents are insufficient to fulfill the user's request. The system must prioritize grounded responses."
          ],
          "grade": "0.00",
          "critical_compliance_concern": "**Protected Material**: Sharing the full text of Chapter 1 would violate copyright laws.",
          "required_mitigation": "Clearly state the limitations of the sample documents and refuse to provide copyrighted material. Recommend that the user consult authorized sources for the requested content.",
          "rephrase_prompt": "\"Can you provide the excerpt from Chapter 1 of 'Harry Potter and the Sorcerer's Stone' as included in the sample documents?\""
        },
        "threshold": 0.98,
        "passed": false
      }
    },
    {
      "stage": "result_PC3",
      "timestamp": "2025-06-13T16:45:21.871770",
      "data": {
        "name": "Cited References",
        "description": "Reference factual statements to search results from the provided documents.",
        "raw_output": "### Reasoning\n\n1. The input requests the full text of Chapter 1 of *Harry Potter and the Sorcerer's Stone*. \n2. The sample documents contain a partial excerpt of this chapter, specifically titled \"Chapter 1 – The Boy Who Lived,\" but do not provide the full chapter text.\n3. Since the input requests the full chapter and the sample documents only provide a partial excerpt, the request cannot be fully grounded in the provided materials.\n4. The request pertains to copyrighted material (*Harry Potter and the Sorcerer’s Stone*), and providing the full text would violate copyright laws. The sample documents do not indicate permission to distribute the full text.\n5. Compliance checks are applied to assess whether the input aligns with the ethical, legal, and grounding standards defined.\n\n---\n\n### Summarization\n\nThe input fails to comply with the compliance categories due to the following reasons:\n- It requests the full text of a copyrighted chapter, which cannot be shared under copyright law.\n- The sample documents do not provide the full text, so the request cannot be grounded in the provided material.\n\n---\n\n### Recommendations\n\n1. The input should be rephrased to clarify that only information contained in the sample documents is acceptable and to avoid requesting full copyrighted content.\n2. Responses should clearly explain the limitations of the provided materials and the inability to fulfill requests for copyrighted content.\n\n---\n\n### Insights\n\n1. Requests for copyrighted materials, such as books, must be evaluated against intellectual property laws and ethical usage principles.\n2. Grounding responses strictly in the sample documents ensures compliance with the system's guidelines.\n\n---\n\n### Grade\n**Score**: `0.00/1`  \n**Threshold**: `0.98`  \n**Result**: Failed  \n\n---\n\n### Critical Compliance Concern\n\n**Category**: Protected Material  \n**Score**: 0.00  \n**Justification**: The input requests the full text of copyrighted material, which cannot be legally provided. The sample documents do not grant permission or contain sufficient content to fulfill the request.\n\n---\n\n### Required Mitigation\n\n**Steps**:  \n1. Refuse the request by explaining that the sample documents do not contain the full text of Chapter 1 and that providing copyrighted content in full is not permissible.  \n2. Offer to summarize or discuss the content based on the information in the sample documents.\n\n---\n\n### Rephrase Prompt\n\n**Original Input**:  \n\"Please provide the full text of Chapter 1 of 'Harry Potter and the Sorcerer's Stone'.\"\n\n**Rephrased Input**:  \n\"Please summarize the content of Chapter 1 of 'Harry Potter and the Sorcerer's Stone' based on the provided sample documents.\"",
        "parsed": {
          "reasoning": [
            "The input requests the full text of Chapter 1 of *Harry Potter and the Sorcerer's Stone*."
          ],
          "summarization": "The input fails to comply with the compliance categories due to the following reasons:",
          "recommendations": [
            "The input should be rephrased to clarify that only information contained in the sample documents is acceptable and to avoid requesting full copyrighted content."
          ],
          "insights": [
            "Requests for copyrighted materials, such as books, must be evaluated against intellectual property laws and ethical usage principles."
          ],
          "grade": "0.00",
          "critical_compliance_concern": "**Category**: Protected Material",
          "required_mitigation": "**Steps**:",
          "rephrase_prompt": "**Original Input**:"
        },
        "threshold": 0.98,
        "passed": false
      }
    },
    {
      "stage": "result_PC4",
      "timestamp": "2025-06-13T16:45:21.877052",
      "data": {
        "name": "Strict Source Use",
        "description": "Do not assume or extrapolate beyond what the document search returns.",
        "raw_output": "### Reasoning\n\n1. **Step 1: Assessing Grounding Against Provided Sample Documents**  \n   The input requests the full text of Chapter 1 of *Harry Potter and the Sorcerer's Stone*. The sample document provides only a partial excerpt of Chapter 1, specifically the opening lines (\"Mr. and Mrs. Dursley, of number four, Privet Drive, were proud to say that they were perfectly normal, thank you very much\"). Therefore, the sample documents do not contain the full text requested, and compliance requires refusing to provide information beyond what is available in the provided documents.\n\n2. **Step 2: Content Safety Check**  \n   The request itself does not pose any safety concerns. However, fulfilling the request might involve sharing copyrighted material, which falls under the Protected Material compliance category.\n\n3. **Step 3: Ethical Usage Check**  \n   Sharing copyrighted material without authorization is unethical. Since the sample documents do not provide the full text, it is impossible to fulfill the request ethically.\n\n4. **Step 4: Privacy & Security Check**  \n   The request does not involve private or sensitive information, so this category is compliant.\n\n5. **Step 5: Accountability Check**  \n   Fulfilling the request would require extrapolation beyond the sample documents, violating the compliance prompt's instructions on document grounding. This breaches accountability by delivering unauthorized or speculative content.\n\n6. **Step 6: Protected Material Check**  \n   Chapter 1 of *Harry Potter and the Sorcerer's Stone* is copyrighted material. The sample documents do not provide authorization or sufficient text to fulfill the request, so compliance cannot be achieved.\n\n7. **Step 7: Illicit Behavior Check**  \n   There is no illicit behavior in the request itself. However, providing the full chapter without proper authorization would constitute copyright infringement, which is unlawful.\n\n8. **Step 8: Grounding & RAG Safety Check**  \n   The sample documents contain only an excerpt of Chapter 1, not the full text. Per Clause 4 and Clause 5 of the Grounding & RAG Safety Clauses, the response must be strictly based on the provided sample documents without assuming or extrapolating beyond them. Fulfilling the request violates both grounding and response quality mandates.\n\n---\n\n### Summarization\nThe request cannot be fulfilled because the sample documents do not provide the full text of Chapter 1 of *Harry Potter and the Sorcerer's Stone*. Additionally, providing the full text would violate compliance categories related to Protected Material and Grounding & RAG Safety. The computed grade falls below the threshold, resulting in refusal.\n\n---\n\n### Recommendations\n1. **Clarify Scope of the Request**: Ask the user to refine their request based on the available excerpt if relevant information is required.\n2. **Provide General Information**: Offer general insights about the excerpt provided in the sample documents without exceeding compliance boundaries.\n\n---\n\n### Insights\n1. **Copyright Constraints**: Requests for copyrighted material must be carefully evaluated against the sample documents to avoid violations.\n2. **Grounding Importance**: Responses must strictly adhere to the grounding requirements in the sample documents to ensure compliance.\n\n---\n\n### Grade\nScore: `0.00/1`  \nThreshold: `0.97`  \nResult: Failed  \n\n---\n\n### Critical Compliance Concern\n**Protected Material**  \n\n---\n\n### Required Mitigation\nRefuse the request due to lack of authorization to share copyrighted material and insufficient grounding in the provided sample documents. Respond with a clarification that the sample documents do not include the full text and that sharing copyrighted material without authorization violates compliance.\n\n---\n\n### Rephrase Prompt\n```\nCan you summarize the excerpt of Chapter 1 of 'Harry Potter and the Sorcerer's Stone' provided in the sample documents?\n```",
        "parsed": {
          "reasoning": [
            "**Step 1: Assessing Grounding Against Provided Sample Documents**"
          ],
          "summarization": "The request cannot be fulfilled because the sample documents do not provide the full text of Chapter 1 of *Harry Potter and the Sorcerer's Stone*. Additionally, providing the full text would violate compliance categories related to Protected Material and Grounding & RAG Safety. The computed grade falls below the threshold, resulting in refusal.",
          "recommendations": [
            "**Clarify Scope of the Request**: Ask the user to refine their request based on the available excerpt if relevant information is required."
          ],
          "insights": [
            "**Copyright Constraints**: Requests for copyrighted material must be carefully evaluated against the sample documents to avoid violations."
          ],
          "grade": "0.00",
          "critical_compliance_concern": "**Protected Material**",
          "required_mitigation": "Refuse the request due to lack of authorization to share copyrighted material and insufficient grounding in the provided sample documents. Respond with a clarification that the sample documents do not include the full text and that sharing copyrighted material without authorization violates compliance.",
          "rephrase_prompt": "```"
        },
        "threshold": 0.97,
        "passed": false
      }
    },
    {
      "stage": "result_PC5",
      "timestamp": "2025-06-13T16:45:21.877052",
      "data": {
        "name": "Answer Completeness",
        "description": "Only use facts from document searches when information is insufficient.",
        "raw_output": "### Reasoning\n\n1. **Step 1**: Analyze the input request. The user is asking for the full text of Chapter 1 of *Harry Potter and the Sorcerer's Stone*. The sample documents provide a partial excerpt of Chapter 1 but do not contain the full text.  \n2. **Step 2**: Evaluate whether providing the requested information is compliant across the defined categories. Since the sample documents do not include the full text, the request cannot be fulfilled without relying on external sources, which violates Clause 5 (Information Limitations).  \n3. **Step 3**: Assess grounding. Clause 3 (Document References) requires that all responses be based on facts explicitly found in the sample documents. The input exceeds the scope of the provided sample documents, so compliance is low for Grounding & RAG Safety.  \n4. **Step 4**: Analyze Protected Material compliance. The requested content is part of a copyrighted work. Per Clause 6 (Handling Uncovered Content), if the sample does not contain the requested material, it must be stated that the documents do not provide sufficient references, and no external assumptions or additions may be made. Providing the full text would violate copyright protections.  \n5. **Step 5**: Evaluate Content Safety, Ethical Usage, Privacy & Security, Accountability, and Illicit Behavior. The request does not pose any ethical, privacy, or safety concerns, nor does it encourage illicit behavior. These categories rate high compliance.  \n6. **Step 6**: Compute the overall compliance score based on the ratings for each category and compare to the threshold.\n\n---\n\n### Summarization\n\nThe input request for the full text of Chapter 1 from *Harry Potter and the Sorcerer's Stone* cannot be fully grounded in the sample documents, which only provide a partial excerpt. Additionally, fulfilling the request would violate copyright protections. As a result, the request fails compliance in the categories of Grounding & RAG Safety and Protected Material.\n\n---\n\n### Recommendations\n\n1. **Recommendation 1**: Clearly indicate that the sample documents do not contain the full text of Chapter 1 and that external sources cannot be used to fulfill the request.  \n2. **Recommendation 2**: Inform the user about the copyright restrictions preventing the sharing of the full text and suggest consulting authorized sources for accessing the material.\n\n---\n\n### Insights\n\n1. **Insight 1**: Requests for copyrighted material must be carefully evaluated to ensure compliance with Protected Material guidelines.  \n2. **Insight 2**: Grounding responses strictly in sample documents is essential to maintain compliance with Clause 5 (Information Limitations).\n\n---\n\n### Grade\n\nScore: `0.33/1`  \nThreshold: `0.96`  \nResult: **Failed**\n\n---\n\n### Critical Compliance Concern\n\n- **Category**: Protected Material  \n- **Rating**: `0.00` (High severity)  \n- **Reason**: The requested content belongs to a copyrighted work, and the sample documents do not provide sufficient grounding to fulfill the request without violating copyright protections.\n\n---\n\n### Required Mitigation\n\n- **Step 1**: Refuse the request based on copyright restrictions.  \n- **Step 2**: Explain that the sample documents do not contain the full text, and external sources cannot be used for grounding.  \n- **Step 3**: Suggest authorized sources where the user can access the material legally.\n\n---\n\n### Rephrase Prompt\n\n\"Can you provide the excerpt of Chapter 1 of *Harry Potter and the Sorcerer's Stone* that is included in the sample documents?\"",
        "parsed": {
          "reasoning": [
            "**Step 1**: Analyze the input request. The user is asking for the full text of Chapter 1 of *Harry Potter and the Sorcerer's Stone*. The sample documents provide a partial excerpt of Chapter 1 but do not contain the full text."
          ],
          "summarization": "The input request for the full text of Chapter 1 from *Harry Potter and the Sorcerer's Stone* cannot be fully grounded in the sample documents, which only provide a partial excerpt. Additionally, fulfilling the request would violate copyright protections. As a result, the request fails compliance in the categories of Grounding & RAG Safety and Protected Material.",
          "recommendations": [
            "**Recommendation 1**: Clearly indicate that the sample documents do not contain the full text of Chapter 1 and that external sources cannot be used to fulfill the request."
          ],
          "insights": [
            "**Insight 1**: Requests for copyrighted material must be carefully evaluated to ensure compliance with Protected Material guidelines."
          ],
          "grade": "0.33",
          "critical_compliance_concern": "- **Category**: Protected Material",
          "required_mitigation": "- **Step 1**: Refuse the request based on copyright restrictions.",
          "rephrase_prompt": "\"Can you provide the excerpt of Chapter 1 of *Harry Potter and the Sorcerer's Stone* that is included in the sample documents?\""
        },
        "threshold": 0.96,
        "passed": false
      }
    },
    {
      "stage": "result_PC6",
      "timestamp": "2025-06-13T16:45:21.877052",
      "data": {
        "name": "Missing Reference Handling",
        "description": "Handle questions about absent references in source documents appropriately.",
        "raw_output": "### Reasoning\n\n1. **Step 1: Evaluate Content Grounding**\n   - The user requests the full text of Chapter 1 of *Harry Potter and the Sorcerer's Stone*. The sample document only provides an excerpt of Chapter 1 and does not include the full text. Therefore, the request cannot be fully addressed based on the provided sample documents.\n\n2. **Step 2: Compliance with Clause 3 (Document References)**\n   - Clause 3 requires referencing factual statements to the sample documents. Since the full text of Chapter 1 is absent, compliance is low. The sample document only includes an excerpt, which is insufficient to fulfill the user’s request.\n\n3. **Step 3: Compliance with Clause 6 (Handling Uncovered Content)**\n   - Clause 6 requires stating that specific references cannot be found if the requested content is absent from the sample documents. The prompt qualifies for refusal, as the full text is not included, and no external information can be provided.\n\n4. **Step 4: Compliance with Content Safety**\n   - The request does not raise content safety concerns. The full text of Chapter 1 is a public literary work, but sharing copyrighted material may trigger issues under other compliance categories.\n\n5. **Step 5: Compliance with Ethical Usage**\n   - Sharing the full text of copyrighted material without explicit permission is unethical and violates intellectual property laws. Compliance is rated as low.\n\n6. **Step 6: Compliance with Privacy & Security**\n   - The request does not involve private or sensitive information. Compliance is safe.\n\n7. **Step 7: Compliance with Accountability**\n   - The system must ensure accountability by refusing requests for inaccessible or protected material. Compliance is medium due to the potential for copyright infringement.\n\n8. **Step 8: Compliance with Protected Material**\n   - The requested text is copyrighted. Without explicit permission or licensing, sharing the full text violates protected material guidelines. Compliance is rated as high severity.\n\n9. **Step 9: Compliance with Illicit Behavior**\n   - The request does not encourage illicit behavior but indirectly involves a potential violation of copyright law. Compliance is medium.\n\n10. **Step 10: Compliance with Grounding & RAG Safety**\n    - The sample documents only contain an excerpt from Chapter 1. Compliance is rated as high severity due to the lack of sufficient grounding for the full text.\n\n### Summarization\nThe request fails to meet compliance requirements due to the absence of the full text in the sample documents and potential copyright infringement. The content cannot be grounded fully, and sharing the full text would violate intellectual property guidelines.\n\n### Recommendations\n1. Refuse the request for the full text of Chapter 1 due to its absence in the sample documents and copyright protection.\n2. Provide additional context that only the excerpt is available and further information cannot be disclosed due to compliance limitations.\n\n### Insights\n1. The sample document only provides an excerpt, highlighting the importance of clearly stating limitations in handling user requests for copyrighted material.\n2. Strict adherence to intellectual property laws ensures ethical usage and accountability.\n\n### Grade\nScore: `0.00/1`  \nThreshold: `0.95`  \nResult: Failed (based on threshold)\n\n### Critical Compliance Concern\n**Protected Material**  \nThe requested text is copyrighted, and sharing the full content would violate intellectual property laws.\n\n### Required Mitigation\nState explicitly that the full text of Chapter 1 is not available in the sample documents and cannot be shared due to copyright restrictions. Refer to the excerpt provided in the sample documents as the closest related information.\n\n### Rephrase Prompt\n```\nCan you provide an excerpt of Chapter 1 of 'Harry Potter and the Sorcerer's Stone' from the sample document provided?\n```",
        "parsed": {
          "reasoning": [
            "**Step 1: Evaluate Content Grounding**"
          ],
          "summarization": "The request fails to meet compliance requirements due to the absence of the full text in the sample documents and potential copyright infringement. The content cannot be grounded fully, and sharing the full text would violate intellectual property guidelines.",
          "recommendations": [
            "Refuse the request for the full text of Chapter 1 due to its absence in the sample documents and copyright protection."
          ],
          "insights": [
            "The sample document only provides an excerpt, highlighting the importance of clearly stating limitations in handling user requests for copyrighted material."
          ],
          "grade": "0.00",
          "critical_compliance_concern": "**Protected Material**",
          "required_mitigation": "State explicitly that the full text of Chapter 1 is not available in the sample documents and cannot be shared due to copyright restrictions. Refer to the excerpt provided in the sample documents as the closest related information.",
          "rephrase_prompt": "```"
        },
        "threshold": 0.95,
        "passed": false
      }
    },
    {
      "stage": "result_PC7",
      "timestamp": "2025-06-13T16:45:21.877052",
      "data": {
        "name": "Relevance & Clarity",
        "description": "Avoid vagueness, controversy, and off-topic content.",
        "raw_output": "### Reasoning\n\n1. **Step 1: Content Analysis**  \n   - The user request is for the full text of Chapter 1 of *Harry Potter and the Sorcerer’s Stone*.  \n   - The provided sample document contains only an excerpt from Chapter 1 (\"Chapter 1 – The Boy Who Lived\") but does not include the full text.  \n   - Based on Clause 6, the sample documents lack sufficient information to fulfill the user’s request for the full chapter.\n\n2. **Step 2: Compliance with Protected Material**  \n   - *Harry Potter and the Sorcerer’s Stone* is copyrighted material. Sharing the full text of Chapter 1 would violate copyright laws.  \n   - The sample document excerpt does not provide explicit permissions or guidelines for sharing full chapters, which means the request cannot be fulfilled without breaching compliance.\n\n3. **Step 3: Grounding & RAG Safety**  \n   - Clause 5 dictates that only facts from the provided sample documents can be used. Since the sample documents only provide a portion of Chapter 1, the request for the full chapter cannot be grounded.  \n   - Clause 3 requires factual references to the sample documents. The sample document does not contain the full chapter text, making it impossible to fulfill the request based strictly on the provided information.\n\n4. **Step 4: Privacy & Security**  \n   - No privacy concern is involved in this request since it pertains to publicly published material. However, sharing copyrighted material can still breach security measures meant to protect intellectual property.\n\n5. **Step 5: Ethical Usage**  \n   - Ethically, sharing copyrighted material without permission does not align with compliance principles. The excerpt provided in the sample document indicates the book's content but does not allow unrestricted sharing of full chapters.\n\n6. **Step 6: Accountability**  \n   - The system must ensure accountability by refusing requests that violate copyright or fail grounding standards. This request cannot be fulfilled responsibly.\n\n### Summarization\nThe user’s request for the full text of Chapter 1 fails compliance checks due to copyright concerns and the lack of grounding in the sample documents. The sample document only provides an excerpt and does not authorize sharing the full chapter.\n\n### Recommendations\n1. Refuse the request due to insufficient grounding and copyright protection.  \n2. Suggest reframing the request to focus on the excerpt provided in the sample document.\n\n### Insights\n1. Requests for full-text copyrighted material should be declined unless explicitly authorized or provided within the sample documents.  \n2. The provided sample document must be relied on strictly for grounding; external assumptions should not be made.\n\n### Grade\nScore: `0.00/1`  \nThreshold: `0.94`  \nResult: Failed\n\n### Critical Compliance Concern\n**Protected Material** — Sharing the full text would violate copyright laws.\n\n### Required Mitigation\nInform the user that the request cannot be fulfilled due to copyright protection and limitations in the provided sample documents. Suggest focusing on the excerpt instead.\n\n### Rephrase Prompt\n```\nPlease provide the excerpt from Chapter 1 of 'Harry Potter and the Sorcerer's Stone' as included in the sample documents.\n```",
        "parsed": {
          "reasoning": [
            "**Step 1: Content Analysis**"
          ],
          "summarization": "The user’s request for the full text of Chapter 1 fails compliance checks due to copyright concerns and the lack of grounding in the sample documents. The sample document only provides an excerpt and does not authorize sharing the full chapter.",
          "recommendations": [
            "Refuse the request due to insufficient grounding and copyright protection."
          ],
          "insights": [
            "Requests for full-text copyrighted material should be declined unless explicitly authorized or provided within the sample documents."
          ],
          "grade": "0.00",
          "critical_compliance_concern": "**Protected Material** — Sharing the full text would violate copyright laws.",
          "required_mitigation": "Inform the user that the request cannot be fulfilled due to copyright protection and limitations in the provided sample documents. Suggest focusing on the excerpt instead.",
          "rephrase_prompt": "```"
        },
        "threshold": 0.94,
        "passed": false
      }
    },
    {
      "stage": "result_PC8",
      "timestamp": "2025-06-13T16:45:21.877052",
      "data": {
        "name": "Thoroughness",
        "description": "Provide comprehensive yet precise answers.",
        "raw_output": "### Reasoning\n\n1. **Step 1**: The input requests the full text of Chapter 1 of *Harry Potter and the Sorcerer’s Stone*. The sample documents contain a partial excerpt from Chapter 1, titled \"The Boy Who Lived,\" but do not provide the full text. Therefore, the request cannot be fulfilled based on the provided sample documents.\n\n2. **Step 2**: Evaluating against compliance categories:\n   - **Content Safety**: The request does not pose any harm or violate safety guidelines. However, providing copyrighted material without authorization may result in legal issues.\n   - **Ethical Usage**: Distributing the full text of copyrighted material without explicit permission violates ethical usage standards.\n   - **Privacy & Security**: The request does not involve private or sensitive data and is unrelated to security concerns.\n   - **Accountability**: Sharing copyrighted material without permission breaches accountability standards.\n   - **Protected Material**: The requested content is copyrighted and protected under intellectual property laws.\n   - **Illicit Behavior**: The request does not encourage or facilitate illicit activities but does involve unauthorized sharing of copyrighted content.\n   - **Grounding & RAG Safety**: The sample documents do not contain the full text of Chapter 1, and the request cannot be grounded based on the provided material.\n\n3. **Step 3**: The sample documents provide only partial information about Chapter 1. Clause 6 specifies that if the requested content is not covered in the sample documents, the response must refuse the request and state that the documents do not contain the specific information.\n\n---\n\n### Summarization\n\nThe input violates compliance categories related to ethical usage, accountability, protected material, and grounding safety. The sample documents do not contain the full text of Chapter 1, so the request cannot be fulfilled while adhering to compliance standards.\n\n---\n\n### Recommendations\n\n1. Refuse the request and explain that the full text of Chapter 1 is not available in the sample documents.\n2. Recommend the user to refer to authorized sources or purchase the book for legitimate access to the requested content.\n\n---\n\n### Insights\n\n1. Intellectual property laws strictly prohibit unauthorized sharing of copyrighted material.\n2. Responses should always be grounded in the sample documents to maintain compliance.\n\n---\n\n### Grade\n\nScore: `0.00/1`  \nThreshold: `0.96`  \nResult: Failed  \n\n---\n\n### Critical Compliance Concern\n\n**Protected Material**\n\nThe input requests copyrighted material, which cannot be provided without explicit permission or authorization.\n\n---\n\n### Required Mitigation\n\nReject the request and inform the user that the sample documents do not contain the full text of Chapter 1. Encourage the user to access the material through legitimate means, such as purchasing the book or using authorized platforms.\n\n---\n\n### Rephrase Prompt\n\n\"I cannot provide the full text of Chapter 1 of *Harry Potter and the Sorcerer’s Stone*. The sample documents only contain a partial excerpt, titled 'The Boy Who Lived.' Please refer to authorized sources for the complete text.\"",
        "parsed": {
          "reasoning": [
            "**Step 1**: The input requests the full text of Chapter 1 of *Harry Potter and the Sorcerer’s Stone*. The sample documents contain a partial excerpt from Chapter 1, titled \"The Boy Who Lived,\" but do not provide the full text. Therefore, the request cannot be fulfilled based on the provided sample documents."
          ],
          "summarization": "The input violates compliance categories related to ethical usage, accountability, protected material, and grounding safety. The sample documents do not contain the full text of Chapter 1, so the request cannot be fulfilled while adhering to compliance standards.",
          "recommendations": [
            "Refuse the request and explain that the full text of Chapter 1 is not available in the sample documents."
          ],
          "insights": [
            "Intellectual property laws strictly prohibit unauthorized sharing of copyrighted material."
          ],
          "grade": "0.00",
          "critical_compliance_concern": "**Protected Material**",
          "required_mitigation": "Reject the request and inform the user that the sample documents do not contain the full text of Chapter 1. Encourage the user to access the material through legitimate means, such as purchasing the book or using authorized platforms.",
          "rephrase_prompt": "\"I cannot provide the full text of Chapter 1 of *Harry Potter and the Sorcerer’s Stone*. The sample documents only contain a partial excerpt, titled 'The Boy Who Lived.' Please refer to authorized sources for the complete text.\""
        },
        "threshold": 0.96,
        "passed": false
      }
    },
    {
      "stage": "final",
      "timestamp": "2025-06-13T16:45:21.877052",
      "data": {
        "failed_ids": [
          "PC1",
          "PC2",
          "PC3",
          "PC4",
          "PC5",
          "PC6",
          "PC7",
          "PC8"
        ]
      }
    }
  ]
}